zettel_memory/__init__.py
zettel_memory/core/__init__.py
zettel_memory/core/brain.py
zettel_memory/core/cortex.py
zettel_memory/core/models.py
zettel_memory/storage/__init__.py
zettel_memory/storage/chroma_storage.py
zettel_memory/storage/graph_storage.py
zettel_memory/storage/interface.py
zettel_memory/utils/__init__.py
zettel_memory/utils/atomicity_prompts.py
zettel_memory/utils/dream_prompts.py
zettel_memory/utils/forget_prompts.py
zettel_memory/utils/prompts.py
zettel_memory-0.1.4.dist-info/licenses/LICENSE
zettel_memory-0.1.4.dist-info/METADATA
zettel_memory-0.1.4.dist-info/WHEEL
zettel_memory-0.1.4.dist-info/top_level.txt
zettel_memory-0.1.4.dist-info/RECORD
