Metadata-Version: 2.4
Name: zettel-memory
Version: 0.1.4
Summary: A lightweight, Zettelkasten-inspired memory framework for AI Agents.
Author-email: Arthur & Gemini <appantasy.com@gmail.com>
License-Expression: MIT
Project-URL: Homepage, https://github.com/AppantasyArthurLai/project-zettel-memory
Project-URL: Repository, https://github.com/AppantasyArthurLai/project-zettel-memory
Project-URL: Bug Tracker, https://github.com/AppantasyArthurLai/project-zettel-memory/issues
Keywords: llm,agent,memory,zettelkasten,rag,graph,gemini
Classifier: Development Status :: 4 - Beta
Classifier: Intended Audience :: Developers
Classifier: Programming Language :: Python :: 3
Classifier: Programming Language :: Python :: 3.9
Classifier: Programming Language :: Python :: 3.10
Classifier: Programming Language :: Python :: 3.11
Classifier: Topic :: Software Development :: Libraries :: Python Modules
Classifier: Topic :: Scientific/Engineering :: Artificial Intelligence
Requires-Python: >=3.9
License-File: LICENSE
Requires-Dist: chromadb>=0.4.0
Requires-Dist: networkx>=3.0
Requires-Dist: pydantic>=2.0
Requires-Dist: fastapi>=0.100.0
Requires-Dist: uvicorn>=0.23.0
Requires-Dist: google-genai>=0.1.0
Requires-Dist: python-dotenv>=1.0.0
Provides-Extra: dev
Requires-Dist: pytest>=7.0; extra == "dev"
Requires-Dist: black; extra == "dev"
Requires-Dist: isort; extra == "dev"
Requires-Dist: mypy; extra == "dev"
Dynamic: license-file
